{"name":"NanoCMS","tagline":"Edit SQLite databases on your Mac","body":"# NanoCMS\r\n\r\n### Introduction:\r\nNanoCMS is a very simple app that can edit SQLite database's\r\n\r\n### Features:\r\n- OSX 10.5++\r\n- Free and OpenSource\r\n- 100% hack Proof\r\n- Tiny footprint only 0.25mb\r\n\r\n### Example:\r\nid  | first-name | last-name | title | age\r\n--- | ---------- | ----------| ----- | ---\r\n1  | Oliver | Knight | Quant | 25\r\n2  | Michael | Smiht | Analyst | 33\r\n\r\nUpdate --> Row value --> Choose row --> Choose value --> \"Smith\"\r\n","google":"","note":"Don't delete this file! It's used internally to help with page regeneration."}